fiesta/__init__.py
fiesta/fiesta.py
fiesta/util.py
fiesta_nlp-0.0.1.dist-info/AUTHORS.txt
fiesta_nlp-0.0.1.dist-info/LICENSE
fiesta_nlp-0.0.1.dist-info/METADATA
fiesta_nlp-0.0.1.dist-info/WHEEL
fiesta_nlp-0.0.1.dist-info/top_level.txt
fiesta_nlp-0.0.1.dist-info/RECORD
