Metadata-Version: 2.1
Name: fiesta-nlp
Version: 0.0.1
Summary: Fast IdEntification of State-of-The-Art models using adaptive bandit algorithms
Home-page: https://github.com/apmoore1/fiesta
Author: Andrew Moore, Henry Moss
Author-email: andrew.p.moore94@gmail.com
License: Apache License 2.0
Platform: UNKNOWN
Classifier: Development Status :: 3 - Alpha
Classifier: Programming Language :: Python :: 3.6
Requires-Python: >=3.6.1
Requires-Dist: numpy
Requires-Dist: scipy
